dmtree.py
downward_mtree-1.0.4.dist-info/LICENSE
downward_mtree-1.0.4.dist-info/METADATA
downward_mtree-1.0.4.dist-info/WHEEL
downward_mtree-1.0.4.dist-info/top_level.txt
downward_mtree-1.0.4.dist-info/RECORD
